water_masses/__init__.py
water_masses/constants.py
water_masses/data/__init__.py
water_masses/data/copernicus-reanalysis.yml
water_masses/decompose.py
water_masses/filter_month.py
water_masses/filtering.py
water_masses/origin/__init__.py
water_masses/origin/pca.py
water_masses/processing.py
water_masses/py.typed
water_masses/spgsi.py
water_masses/time_series.py
water_masses/tracmass/__init__.py
water_masses/tracmass/io.py
water_masses/tracmass/seeding.py
water_masses/transform.py
water_masses/version.py
water_masses-2022.1.1.dist-info/LICENSE
water_masses-2022.1.1.dist-info/WHEEL
water_masses-2022.1.1.dist-info/METADATA
water_masses-2022.1.1.dist-info/RECORD
