Metadata-Version: 2.1
Name: water-masses
Version: 2022.1.1
Summary: Analysis of the northern European shelf seas
Home-page: https://github.com/shelf-sea/water-masses
License: GPL3
Requires-Python: >=3.8,<3.10
Classifier: Development Status :: 2 - Pre-Alpha
Classifier: Intended Audience :: Science/Research
Classifier: License :: OSI Approved :: GNU General Public License v3 or later (GPLv3+)
Classifier: License :: Other/Proprietary License
Classifier: Operating System :: OS Independent
Classifier: Programming Language :: Python :: 3
Classifier: Programming Language :: Python :: 3.8
Classifier: Programming Language :: Python :: 3.9
Classifier: Topic :: Software Development :: Libraries :: Python Modules
Requires-Dist: cf-xarray (>=0.5,<1.0)
Requires-Dist: cftime (>=1.2,<2.0)
Requires-Dist: dask (>=2021)
Requires-Dist: eofs (>=1.4,<2.0)
Requires-Dist: h5netcdf (>=1)
Requires-Dist: intake (>=0.6,<1.0)
Requires-Dist: intake-xarray (>=0.4,<1.0)
Requires-Dist: nc-time-axis (>=1.2,<2.0)
Requires-Dist: netcdf4 (>=1.5,<2.0)
Requires-Dist: numpy (>=1.19,<2.0)
Requires-Dist: pandas (>=1.1,<2.0)
Requires-Dist: scipy (>=1.7,<2.0)
Requires-Dist: statsmodels (>=0.12,<1.0)
Requires-Dist: xarray (>=2022)
Project-URL: Repository, https://github.com/shelf-sea/water-masses
